Workbook

Sheet Campaign Data
A1: Campaign-Level Performance — FY2025
A2: Blue = source data (from ad platform exports). Black = formulas.
A4: Campaign ID | B4: Campaign Name | C4: Channel | D4: Geography | E4: Segment | F4: Impressions | G4: Clicks | H4: Leads | I4: Purchases | J4: Revenue ($) | K4: Cost ($) | L4: CTR % | M4: CPC ($) | N4: CPL ($) | O4: Conv. Rate % | P4: CAC ($) | Q4: ROAS (x) | R4: ROI %
A5: C035 | B5: Email_Returning_May2025 | C5: Email | D5: North America | E5: Price-Sensitive | F5: 466187 | G5: 20370 | H5: 3987 | I5: 1097 | J5: 69222.98 | K5: 3034.44 | L5: =IF(F5=0,0,G5/F5) -> 0.043694912 | M5: =IF(G5=0,0,K5/G5) -> 0.14896613 | N5: =IF(H5=0,0,K5/H5) -> 0.76108352 | O5: =IF(G5=0,0,I5/G5) -> 0.053853706 | P5: =IF(I5=0,0,K5/I5) -> 2.7661258 | Q5: =IF(K5=0,0,J5/K5) -> 22.81244 | R5: =IF(K5=0,0,(J5-K5)/K5) -> 21.81244
A6: C036 | B6: Email_New_Jan2025 | C6: Email | D6: North America | E6: High-Value | F6: 526568 | G6: 23155 | H6: 4563 | I6: 1233 | J6: 77679.17 | K6: 3424.21 | L6: =IF(F6=0,0,G6/F6) -> 0.043973428 | M6: =IF(G6=0,0,K6/G6) -> 0.1478821 | N6: =IF(H6=0,0,K6/H6) -> 0.75042954 | O6: =IF(G6=0,0,I6/G6) -> 0.053249838 | P6: =IF(I6=0,0,K6/I6) -> 2.7771371 | Q6: =IF(K6=0,0,J6/K6) -> 22.685282 | R6: =IF(K6=0,0,(J6-K6)/K6) -> 21.685282
A7: C023 | B7: Email_Price-Sensitive_Jun2025 | C7: Email | D7: North America | E7: Returning Customers | F7: 361777 | G7: 15999 | H7: 3117 | I7: 835 | J7: 52614.76 | K7: 2368.41 | L7: =IF(F7=0,0,G7/F7) -> 0.044223375 | M7: =IF(G7=0,0,K7/G7) -> 0.14803488 | N7: =IF(H7=0,0,K7/H7) -> 0.75983638 | O7: =IF(G7=0,0,I7/G7) -> 0.052190762 | P7: =IF(I7=0,0,K7/I7) -> 2.8364192 | Q7: =IF(K7=0,0,J7/K7) -> 22.215225 | R7: =IF(K7=0,0,(J7-K7)/K7) -> 21.215225
A8: C029 | B8: Email_New_May2025 | C8: Email | D8: Europe | E8: Price-Sensitive | F8: 312726 | G8: 14285 | H8: 2752 | I8: 759 | J8: 47747.24 | K8: 2161.9 | L8: =IF(F8=0,0,G8/F8) -> 0.045678965 | M8: =IF(G8=0,0,K8/G8) -> 0.15134057 | N8: =IF(H8=0,0,K8/H8) -> 0.78557413 | O8: =IF(G8=0,0,I8/G8) -> 0.053132657 | P8: =IF(I8=0,0,K8/I8) -> 2.8483531 | Q8: =IF(K8=0,0,J8/K8) -> 22.085776 | R8: =IF(K8=0,0,(J8-K8)/K8) -> 21.085776
A9: C011 | B9: Email_Price-Sensitive_Jan2025 | C9: Email | D9: North America | E9: Returning Customers | F9: 412751 | G9: 19518 | H9: 3804 | I9: 1050 | J9: 64312.04 | K9: 2932.92 | L9: =IF(F9=0,0,G9/F9) -> 0.04728759 | M9: =IF(G9=0,0,K9/G9) -> 0.15026745 | N9: =IF(H9=0,0,K9/H9) -> 0.77100946 | O9: =IF(G9=0,0,I9/G9) -> 0.053796496 | P9: =IF(I9=0,0,K9/I9) -> 2.7932571 | Q9: =IF(K9=0,0,J9/K9) -> 21.927649 | R9: =IF(K9=0,0,(J9-K9)/K9) -> 20.927649
A10: C013 | B10: Email_Price-Sensitive_May2025 | C10: Email | D10: Europe | E10: High-Value | F10: 520807 | G10: 23969 | H10: 4719 | I10: 1284 | J10: 77368.73 | K10: 3536.84 | L10: =IF(F10=0,0,G10/F10) -> 0.046022807 | M10: =IF(G10=0,0,K10/G10) -> 0.14755893 | N10: =IF(H10=0,0,K10/H10) -> 0.7494893 | O10: =IF(G10=0,0,I10/G10) -> 0.053569194 | P10: =IF(I10=0,0,K10/I10) -> 2.7545483 | Q10: =IF(K10=0,0,J10/K10) -> 21.8751 | R10: =IF(K10=0,0,(J10-K10)/K10) -> 20.8751
A11: C032 | B11: Email_New_Aug2025 | C11: Email | D11: North America | E11: New Customers | F11: 349680 | G11: 16142 | H11: 3262 | I11: 850 | J11: 51984.25 | K11: 2423.92 | L11: =IF(F11=0,0,G11/F11) -> 0.046162205 | M11: =IF(G11=0,0,K11/G11) -> 0.15016231 | N11: =IF(H11=0,0,K11/H11) -> 0.74307787 | O11: =IF(G11=0,0,I11/G11) -> 0.052657663 | P11: =IF(I11=0,0,K11/I11) -> 2.8516706 | Q11: =IF(K11=0,0,J11/K11) -> 21.446355 | R11: =IF(K11=0,0,(J11-K11)/K11) -> 20.446355
A12: C022 | B12: Email_Price-Sensitive_Jan2025 | C12: Email | D12: North America | E12: Returning Customers | F12: 370401 | G12: 16097 | H12: 2916 | I12: 782 | J12: 49276.38 | K12: 2380.74 | L12: =IF(F12=0,0,G12/F12) -> 0.043458306 | M12: =IF(G12=0,0,K12/G12) -> 0.14789961 | N12: =IF(H12=0,0,K12/H12) -> 0.81644033 | O12: =IF(G12=0,0,I12/G12) -> 0.048580481 | P12: =IF(I12=0,0,K12/I12) -> 3.0444246 | Q12: =IF(K12=0,0,J12/K12) -> 20.697926 | R12: =IF(K12=0,0,(J12-K12)/K12) -> 19.697926
A13: C008 | B13: Google_Returning_Sep2025 | C13: Google | D13: APAC | E13: High-Value | F13: 580703 | G13: 20662 | H13: 2918 | I13: 603 | J13: 43888.79 | K13: 6022.8 | L13: =IF(F13=0,0,G13/F13) -> 0.035581011 | M13: =IF(G13=0,0,K13/G13) -> 0.29149163 | N13: =IF(H13=0,0,K13/H13) -> 2.0640164 | O13: =IF(G13=0,0,I13/G13) -> 0.029184009 | P13: =IF(I13=0,0,K13/I13) -> 9.9880597 | Q13: =IF(K13=0,0,J13/K13) -> 7.2871073 | R13: =IF(K13=0,0,(J13-K13)/K13) -> 6.2871073
A14: C025 | B14: Google_High-Value_Mar2025 | C14: Google | D14: APAC | E14: High-Value | F14: 483029 | G14: 17062 | H14: 2318 | I14: 498 | J14: 36137.52 | K14: 15051.13 | L14: =IF(F14=0,0,G14/F14) -> 0.035322931 | M14: =IF(G14=0,0,K14/G14) -> 0.88214336 | N14: =IF(H14=0,0,K14/H14) -> 6.4931536 | O14: =IF(G14=0,0,I14/G14) -> 0.029187669 | P14: =IF(I14=0,0,K14/I14) -> 30.223153 | Q14: =IF(K14=0,0,J14/K14) -> 2.4009838 | R14: =IF(K14=0,0,(J14-K14)/K14) -> 1.4009838
A15: C030 | B15: Google_Price-Sensitive_Jan2025 | C15: Google | D15: North America | E15: New Customers | F15: 139156 | G15: 4745 | H15: 643 | I15: 127 | J15: 9813.29 | K15: 4142.17 | L15: =IF(F15=0,0,G15/F15) -> 0.034098422 | M15: =IF(G15=0,0,K15/G15) -> 0.87295469 | N15: =IF(H15=0,0,K15/H15) -> 6.441944 | O15: =IF(G15=0,0,I15/G15) -> 0.026765016 | P15: =IF(I15=0,0,K15/I15) -> 32.615512 | Q15: =IF(K15=0,0,J15/K15) -> 2.3691181 | R15: =IF(K15=0,0,(J15-K15)/K15) -> 1.3691181
A16: C039 | B16: Google_Price-Sensitive_Jan2025 | C16: Google | D16: Europe | E16: Returning Customers | F16: 337713 | G16: 12125 | H16: 1694 | I16: 357 | J16: 24754.47 | K16: 11170.14 | L16: =IF(F16=0,0,G16/F16) -> 0.035903267 | M16: =IF(G16=0,0,K16/G16) -> 0.92124866 | N16: =IF(H16=0,0,K16/H16) -> 6.5939433 | O16: =IF(G16=0,0,I16/G16) -> 0.029443299 | P16: =IF(I16=0,0,K16/I16) -> 31.288908 | Q16: =IF(K16=0,0,J16/K16) -> 2.2161289 | R16: =IF(K16=0,0,(J16-K16)/K16) -> 1.2161289
... A44: C012 | B44: TikTok_New_Mar2025 | C44: TikTok | D44: North America | E44: Price-Sensitive | F44: 152119 | G44: 2845 | H44: 155 | I44: 5 | J44: 226.13 | K44: 1997.33 | L44: =IF(F44=0,0,G44/F44) -> 0.018702463 | M44: =IF(G44=0,0,K44/G44) -> 0.70204921 | N44: =IF(H44=0,0,K44/H44) -> 12.886 | O44: =IF(G44=0,0,I44/G44) -> 0.0017574692 | P44: =IF(I44=0,0,K44/I44) -> 399.466 | Q44: =IF(K44=0,0,J44/K44) -> 0.11321614 | R44: =IF(K44=0,0,(J44-K44)/K44) -> -0.88678386

Sheet Channel Summary
A1: Channel-Level ROI Summary — FY2025
A2: All figures pull live via SUMIFS from 'Campaign Data'. Edit that sheet and this updates.
A4: Channel | B4: Impressions | C4: Clicks | D4: Leads | E4: Purchases | F4: Revenue ($) | G4: Cost ($) | H4: CTR % | I4: CPC ($) | J4: CAC ($) | K4: ROAS (x) | L4: ROI % | M4: ROAS Rank
A5: Affiliate | B5: =SUMIFS('Campaign Data'!F5:F44,'Campaign Data'!$C$5:$C$44,$A5) -> 822227 | C5: =SUMIFS('Campaign Data'!G5:G44,'Campaign Data'!$C$5:$C$44,$A5) -> 20914 | D5: =SUMIFS('Campaign Data'!H5:H44,'Campaign Data'!$C$5:$C$44,$A5) -> 2299 | E5: =SUMIFS('Campaign Data'!I5:I44,'Campaign Data'!$C$5:$C$44,$A5) -> 389 | F5: =SUMIFS('Campaign Data'!J5:J44,'Campaign Data'!$C$5:$C$44,$A5) -> 27232.18 | G5: =SUMIFS('Campaign Data'!K5:K44,'Campaign Data'!$C$5:$C$44,$A5) -> 19138.83 | H5: =IF(B5=0,0,C5/B5) -> 0.025435798 | I5: =IF(C5=0,0,G5/C5) -> 0.91512049 | J5: =IF(E5=0,0,G5/E5) -> 49.200077 | K5: =IF(G5=0,0,F5/G5) -> 1.4228759 | L5: =IF(G5=0,0,(F5-G5)/G5) -> 0.4228759 | M5: =RANK(K5,$K$5:$K$10) -> 3
A6: Email | B6: =SUMIFS('Campaign Data'!F5:F44,'Campaign Data'!$C$5:$C$44,$A6) -> 3320897 | C6: =SUMIFS('Campaign Data'!G5:G44,'Campaign Data'!$C$5:$C$44,$A6) -> 149535 | D6: =SUMIFS('Campaign Data'!H5:H44,'Campaign Data'!$C$5:$C$44,$A6) -> 29120 | E6: =SUMIFS('Campaign Data'!I5:I44,'Campaign Data'!$C$5:$C$44,$A6) -> 7890 | F6: =SUMIFS('Campaign Data'!J5:J44,'Campaign Data'!$C$5:$C$44,$A6) -> 490205.55 | G6: =SUMIFS('Campaign Data'!K5:K44,'Campaign Data'!$C$5:$C$44,$A6) -> 22263.38 | H6: =IF(B6=0,0,C6/B6) -> 0.045028497 | I6: =IF(C6=0,0,G6/C6) -> 0.14888407 | J6: =IF(E6=0,0,G6/E6) -> 2.8217212 | K6: =IF(G6=0,0,F6/G6) -> 22.018469 | L6: =IF(G6=0,0,(F6-G6)/G6) -> 21.018469 | M6: =RANK(K6,$K$5:$K$10) -> 1
A7: Facebook | B7: =SUMIFS('Campaign Data'!F5:F44,'Campaign Data'!$C$5:$C$44,$A7) -> 4169820 | C7: =SUMIFS('Campaign Data'!G5:G44,'Campaign Data'!$C$5:$C$44,$A7) -> 74724 | D7: =SUMIFS('Campaign Data'!H5:H44,'Campaign Data'!$C$5:$C$44,$A7) -> 6421 | E7: =SUMIFS('Campaign Data'!I5:I44,'Campaign Data'!$C$5:$C$44,$A7) -> 799 | F7: =SUMIFS('Campaign Data'!J5:J44,'Campaign Data'!$C$5:$C$44,$A7) -> 54672.37 | G7: =SUMIFS('Campaign Data'!K5:K44,'Campaign Data'!$C$5:$C$44,$A7) -> 62830.33 | H7: =IF(B7=0,0,C7/B7) -> 0.017920198 | I7: =IF(C7=0,0,G7/C7) -> 0.840832 | J7: =IF(E7=0,0,G7/E7) -> 78.636208 | K7: =IF(G7=0,0,F7/G7) -> 0.87015889 | L7: =IF(G7=0,0,(F7-G7)/G7) -> -0.12984111 | M7: =RANK(K7,$K$5:$K$10) -> 4
A8: Google | B8: =SUMIFS('Campaign Data'!F5:F44,'Campaign Data'!$C$5:$C$44,$A8) -> 2472009 | C8: =SUMIFS('Campaign Data'!G5:G44,'Campaign Data'!$C$5:$C$44,$A8) -> 87105 | D8: =SUMIFS('Campaign Data'!H5:H44,'Campaign Data'!$C$5:$C$44,$A8) -> 11931 | E8: =SUMIFS('Campaign Data'!I5:I44,'Campaign Data'!$C$5:$C$44,$A8) -> 2477 | F8: =SUMIFS('Campaign Data'!J5:J44,'Campaign Data'!$C$5:$C$44,$A8) -> 176641.94 | G8: =SUMIFS('Campaign Data'!K5:K44,'Campaign Data'!$C$5:$C$44,$A8) -> 76538.86 | H8: =IF(B8=0,0,C8/B8) -> 0.035236522 | I8: =IF(C8=0,0,G8/C8) -> 0.87869652 | J8: =IF(E8=0,0,G8/E8) -> 30.899822 | K8: =IF(G8=0,0,F8/G8) -> 2.3078726 | L8: =IF(G8=0,0,(F8-G8)/G8) -> 1.3078726 | M8: =RANK(K8,$K$5:$K$10) -> 2
A9: Instagram | B9: =SUMIFS('Campaign Data'!F5:F44,'Campaign Data'!$C$5:$C$44,$A9) -> 4155481 | C9: =SUMIFS('Campaign Data'!G5:G44,'Campaign Data'!$C$5:$C$44,$A9) -> 57909 | D9: =SUMIFS('Campaign Data'!H5:H44,'Campaign Data'!$C$5:$C$44,$A9) -> 4336 | E9: =SUMIFS('Campaign Data'!I5:I44,'Campaign Data'!$C$5:$C$44,$A9) -> 344 | F9: =SUMIFS('Campaign Data'!J5:J44,'Campaign Data'!$C$5:$C$44,$A9) -> 20524.41 | G9: =SUMIFS('Campaign Data'!K5:K44,'Campaign Data'!$C$5:$C$44,$A9) -> 55022.5 | H9: =IF(B9=0,0,C9/B9) -> 0.013935571 | I9: =IF(C9=0,0,G9/C9) -> 0.95015455 | J9: =IF(E9=0,0,G9/E9) -> 159.94913 | K9: =IF(G9=0,0,F9/G9) -> 0.37301849 | L9: =IF(G9=0,0,(F9-G9)/G9) -> -0.62698151 | M9: =RANK(K9,$K$5:$K$10) -> 5
A10: TikTok | B10: =SUMIFS('Campaign Data'!F5:F44,'Campaign Data'!$C$5:$C$44,$A10) -> 702542 | C10: =SUMIFS('Campaign Data'!G5:G44,'Campaign Data'!$C$5:$C$44,$A10) -> 14856 | D10: =SUMIFS('Campaign Data'!H5:H44,'Campaign Data'!$C$5:$C$44,$A10) -> 815 | E10: =SUMIFS('Campaign Data'!I5:I44,'Campaign Data'!$C$5:$C$44,$A10) -> 34 | F10: =SUMIFS('Campaign Data'!J5:J44,'Campaign Data'!$C$5:$C$44,$A10) -> 1546.6 | G10: =SUMIFS('Campaign Data'!K5:K44,'Campaign Data'!$C$5:$C$44,$A10) -> 10485.46 | H10: =IF(B10=0,0,C10/B10) -> 0.021146067 | I10: =IF(C10=0,0,G10/C10) -> 0.70580641 | J10: =IF(E10=0,0,G10/E10) -> 308.39588 | K10: =IF(G10=0,0,F10/G10) -> 0.14749949 | L10: =IF(G10=0,0,(F10-G10)/G10) -> -0.85250051 | M10: =RANK(K10,$K$5:$K$10) -> 6
A12: TOTAL / BLENDED | B12: =SUM(B5:B10) -> 15642976 | C12: =SUM(C5:C10) -> 405043 | D12: =SUM(D5:D10) -> 54922 | E12: =SUM(E5:E10) -> 11933 | F12: =SUM(F5:F10) -> 770823.05 | G12: =SUM(G5:G10) -> 246279.36 | K12: =IF(G12=0,0,F12/G12) -> 3.1298727 | L12: =IF(G12=0,0,(F12-G12)/G12) -> 2.1298727

Sheet AB Test
A1: Landing Page A/B Test — Statistical Significance
A2: Inputs (blue) are aggregated visitor/conversion counts. All statistics below are live formulas.
A4: Group | B4: Visitors | C4: Conversions | D4: Conversion Rate
A5: Control | B5: 20035 | C5: 1578 | D5: =C5/B5 -> 0.078762166
A6: Variant | B6: 20085 | C6: 1926 | D6: =C6/B6 -> 0.095892457
A9: Pooled proportion (p̂) | B9: =(C5+C6)/(B5+B6) -> 0.087337986
A10: Pooled standard error | B10: =SQRT(B9*(1-B9)*(1/B5+1/B6)) -> 0.0028190738
A11: Absolute uplift (Variant − Control) | B11: =D6-D5 -> 0.017130291
A12: Relative uplift | B12: =B11/D5 -> 0.2174939
A13: Z-statistic | B13: =B11/B10 -> 6.076567
A14: P-value (two-sided) | B14: =2*(1-NORMSDIST(ABS(B13))) -> 1.227827e-09
A15: Significant at α=0.05? | B15: =IF(B14<0.05,"YES","NO") -> YES
A16: Unpooled SE (for CI) | B16: =SQRT(D5*(1-D5)/B5+D6*(1-D6)/B6) -> 0.0028174645
A17: 95% CI lower bound | B17: =B11-1.96*B16 -> 0.01160806
A18: 95% CI upper bound | B18: =B11+1.96*B16 -> 0.022652521
A20: Business Impact Projection
A21: Blended AOV ($) — from Campaign Data | B21: 64.6
A22: Assumed monthly landing-page traffic | B22: 50000
A23: Projected incremental conversions/month | B23: =B22*B11 -> 856.51454
A24: Projected incremental revenue/month ($) | B24: =B23*B21 -> 55330.839
A25: Projected incremental revenue/year ($) | B25: =B24*12 -> 663970.07
A27: Note: traffic assumption (50,000/month) is illustrative — replace with actual landing-page traffic for a precise projection.
